suraj_datalab/__init__.py
suraj_datalab/analyze.py
suraj_datalab/clean.py
suraj_datalab/fold_creator.py
suraj_datalab-0.1.1.dist-info/LICENSE
suraj_datalab-0.1.1.dist-info/METADATA
suraj_datalab-0.1.1.dist-info/WHEEL
suraj_datalab-0.1.1.dist-info/RECORD
