Metadata-Version: 2.1
Name: suraj_datalab
Version: 0.1.1
Summary: A package for data analysis
Author: Suraj Wate
Author-email: suraj.wate@gmail.com
Requires-Python: >=3.12,<4.0
Classifier: Programming Language :: Python :: 3
Classifier: Programming Language :: Python :: 3.12
Requires-Dist: ipython (>=8.26.0,<9.0.0)
Requires-Dist: matplotlib (>=3.9.2,<4.0.0)
Requires-Dist: numpy (>=2.1.0,<3.0.0)
Requires-Dist: pandas (>=2.2.2,<3.0.0)
Requires-Dist: scikit-learn (>=1.5.1,<2.0.0)
Requires-Dist: seaborn (>=0.13.2,<0.14.0)
